chinese_calligraphy/__init__.py
chinese_calligraphy/brush.py
chinese_calligraphy/elements.py
chinese_calligraphy/font.py
chinese_calligraphy/layout.py
chinese_calligraphy/style.py
chinese_calligraphy/types.py
chinese_calligraphy/utils.py
chinese_calligraphy/works/__init__.py
chinese_calligraphy/works/couplet.py
chinese_calligraphy/works/fan.py
chinese_calligraphy/works/handscroll.py
chinese_calligraphy-0.1.1.dist-info/METADATA
chinese_calligraphy-0.1.1.dist-info/WHEEL
chinese_calligraphy-0.1.1.dist-info/licenses/LICENSE
chinese_calligraphy-0.1.1.dist-info/RECORD
