Metadata-Version: 2.4
Name: chinese-calligraphy
Version: 0.1.1
Summary: A Pythonic interface for generating Chinese calligraphy works
Project-URL: Homepage, https://github.com/mountain/chinese-calligraphy
Project-URL: Repository, https://github.com/mountain/chinese-calligraphy
Project-URL: Issues, https://github.com/mountain/chinese-calligraphy/issues
Author: Mingli Yuan
License: MIT License
License-File: LICENSE
Keywords: art,calligraphy,chinese,graphics,pillow,typography
Classifier: Development Status :: 3 - Alpha
Classifier: Intended Audience :: Developers
Classifier: Intended Audience :: Education
Classifier: License :: OSI Approved :: MIT License
Classifier: Operating System :: OS Independent
Classifier: Programming Language :: Python
Classifier: Programming Language :: Python :: 3
Classifier: Programming Language :: Python :: 3 :: Only
Classifier: Programming Language :: Python :: 3.10
Classifier: Programming Language :: Python :: 3.11
Classifier: Programming Language :: Python :: 3.12
Classifier: Programming Language :: Python :: 3.13
Classifier: Topic :: Artistic Software
Classifier: Topic :: Multimedia :: Graphics
Requires-Python: >=3.10
Requires-Dist: pillow>=10.0.0
Provides-Extra: fonttools
Requires-Dist: fonttools>=4.0.0; extra == 'fonttools'
